sci_api_req/__init__.py
sci_api_req/config.py
sci_api_req/providers/__init__.py
sci_api_req/providers/api_provider.py
sci_api_req/providers/NASA/__init__.py
sci_api_req/providers/NASA/apod_provider.py
sci_api_req/providers/NASA/donki_provider.py
sci_api_req/providers/NASA/neows_provider.py
sci_api_req-0.1.1.dist-info/LICENSE
sci_api_req-0.1.1.dist-info/METADATA
sci_api_req-0.1.1.dist-info/WHEEL
sci_api_req-0.1.1.dist-info/top_level.txt
sci_api_req-0.1.1.dist-info/RECORD
